{
  "dependencies": [
    "need_assistance"
  ],
  "tasks": {
    "mining_takes_forever_task": {
      "title": "",
      "icon": {
        "item": {
          "id": "minecraft:air",
          "count": 0
        },
        "type": "heracles:item"
      },
      "type": "heracles:check"
    }
  },
  "rewards": {},
  "display": {
    "subtitle": {
      "text": ""
    },
    "description": [
      "<hr/>",
      "  破壞太多方塊花費太長時間？好吧，我告訴你一個小技巧，可以讓你更快地破壞方塊。",
      "<br/>",
      "  你知道那個墓碑符號( ` )在你的手指附近，很可能不遠離你的左小指嗎？好吧，如果你非常專注地在挖掘的時候按下它，它會破壞很多方塊！但要小心，因為這會縮短挖掘時間，但不會減少你的食物或工具耐久度的消耗。",
      "<br/>",
      "  如果你不喜歡這個預設的符號，你可以隨時在你的腦海中改變它。當我第一次被合併的時候，這個符號和其他的都被稱為「按鍵綁定」。這個特別的叫做「FTB Ultimine」。",
      "<br/>",
      "<item id=\"minecraft:diamond_pickaxe\" scale=\"4\"/>",
      "<hr/>"
    ],
    "groups": {
      "入門指南": {
        "position": [
          -100,
          0
        ]
      }
    },
    "icon": {
      "item": {
        "id": "minecraft:diamond_pickaxe",
        "count": 1,
        "nbt": {
          "Damage": 0
        }
      },
      "type": "heracles:item"
    },
    "icon_background": "heracles:textures/gui/quest_backgrounds/circles.png",
    "title": {
      "translate": "挖礦花費太久！"
    }
  },
  "settings": {
    "unlockNotification": false,
    "showDependencyArrow": true,
    "repeatable": false,
    "individual_progress": false,
    "hidden": "IN_PROGRESS"
  }
}